<annotation>
  <folder>train</folder>
  <filename>AsaS</filename>
  <path>C:\Users\Matteo\Desktop\resized\train\AsaS.jpg</path>
  <source>
    <database>Unknown</database>
  </source>
  <size>
    <width>800</width>
    <height>600</height>
    <depth>3</depth>
  </size>
  <segmented>0</segmented>
  <object>
    <name>cane da caccia</name>
    <pose>Unspecified</pose>
    <truncated>0</truncated>
    <difficult>0</difficult>
    <bndbox>
      <xmin>90</xmin>
      <ymin>27</ymin>
      <xmax>754</xmax>
      <ymax>593</ymax>
    </bndbox>
  </object>
</annotation>
